setup.cfg
setup.py
pyQRadar.egg-info/PKG-INFO
pyQRadar.egg-info/SOURCES.txt
pyQRadar.egg-info/dependency_links.txt
pyQRadar.egg-info/requires.txt
pyQRadar.egg-info/top_level.txt
pyqradar.egg-info/SOURCES.txt
qradar/__init__.py
qradar/pyQRadar.py
qradar/qradarbase.py