Metadata-Version: 1.0
Name: pyqradar
Version: 0.2.1
Summary: QRadar API Library
Home-page: https://github.com/frikky/pyQRadar
Author: @Frikkylikeme
Author-email: fredrik_9490@hotmail.com
License: UNKNOWN
Platform: UNKNOWN
